[
    {
        "frame_id": [
            -1,
            -1,
            -1,
            -1,
            -1,
            114
        ],
        "description": [
            "None",
            "None",
            "None",
            "None",
            "None",
            "next action"
        ]
    },
    {
        "frame_id": [
            -1,
            -1,
            -1,
            -1,
            114,
            596
        ],
        "description": [
            "None",
            "None",
            "None",
            "None",
            "dissect gallbladder",
            "next action"
        ]
    },
    {
        "frame_id": [
            -1,
            -1,
            -1,
            114,
            596,
            660
        ],
        "description": [
            "None",
            "None",
            "None",
            "dissect gallbladder",
            "dissect cystic_duct",
            "next action"
        ]
    },
    {
        "frame_id": [
            -1,
            -1,
            114,
            596,
            660,
            722
        ],
        "description": [
            "None",
            "None",
            "dissect gallbladder",
            "dissect cystic_duct",
            "dissect gallbladder",
            "next action"
        ]
    }
]