[
    {
        "frame_id": [
            -1,
            -1,
            -1,
            -1,
            -1,
            150
        ],
        "description": [
            "None",
            "None",
            "None",
            "None",
            "None",
            "next action"
        ]
    },
    {
        "frame_id": [
            -1,
            -1,
            -1,
            -1,
            150,
            221
        ],
        "description": [
            "None",
            "None",
            "None",
            "None",
            "dissect fat",
            "next action"
        ]
    },
    {
        "frame_id": [
            -1,
            -1,
            -1,
            150,
            221,
            362
        ],
        "description": [
            "None",
            "None",
            "None",
            "dissect fat",
            "dissect gallbladder",
            "next action"
        ]
    },
    {
        "frame_id": [
            -1,
            -1,
            150,
            221,
            362,
            401
        ],
        "description": [
            "None",
            "None",
            "dissect fat",
            "dissect gallbladder",
            "dissect cystic_duct",
            "next action"
        ]
    },
    {
        "frame_id": [
            -1,
            150,
            221,
            362,
            401,
            426
        ],
        "description": [
            "None",
            "dissect fat",
            "dissect gallbladder",
            "dissect cystic_duct",
            "dissect cystic_artery",
            "next action"
        ]
    },
    {
        "frame_id": [
            150,
            221,
            362,
            401,
            426,
            478
        ],
        "description": [
            "dissect fat",
            "dissect gallbladder",
            "dissect cystic_duct",
            "dissect cystic_artery",
            "dissect gallbladder",
            "next action"
        ]
    },
    {
        "frame_id": [
            221,
            362,
            401,
            426,
            478,
            502
        ],
        "description": [
            "dissect gallbladder",
            "dissect cystic_duct",
            "dissect cystic_artery",
            "dissect gallbladder",
            "dissect cystic_artery",
            "next action"
        ]
    }
]